rizapubsub/__init__.py
rizapubsub/demo_pub.py
rizapubsub/demo_sub.py
rizapubsub/pubsub.py
rizapubsub-0.0.1.dist-info/LICENSE
rizapubsub-0.0.1.dist-info/METADATA
rizapubsub-0.0.1.dist-info/WHEEL
rizapubsub-0.0.1.dist-info/top_level.txt
rizapubsub-0.0.1.dist-info/RECORD
